{
  "family": "opsshield/dev",
  "taskRoleArn": "arn:aws:iam::ACCOUNT_ID:role/ecsTaskRole",
  "executionRoleArn": "arn:aws:iam::ACCOUNT_ID:role/ecsExecutionRole",
  "networkMode": "awsvpc",
  "requiresCompatibilities": ["FARGATE"],
  "cpu": "512",
  "memory": "1024",
  "containerDefinitions": [
    {
      "name": "opsshield-app",
      "image": "ACCOUNT_ID.dkr.ecr.REGION.amazonaws.com/opsshield:latest",
      "portMappings": [
        {
          "containerPort": 3000,
          "protocol": "tcp"
        }
      ],
      "environment": [
        {
          "name": "NODE_ENV",
          "value": "development"
        },
        {
          "name": "PORT",
          "value": "3000"
        },
        {
          "name": "PRISMA_QUERY_ENGINE_LIBRARY",
          "value": "/app/node_modules/@prisma/engines/libquery_engine-debian-openssl-3.0.x.so.node"
        }
      ],
      "secrets": [
        {
          "name": "DATABASE_URL",
          "valueFrom": "arn:aws:secretsmanager:REGION:ACCOUNT_ID:secret:oppshield/dev/database-url"
        },
        {
          "name": "JWT_SECRET",
          "valueFrom": "arn:aws:secretsmanager:REGION:ACCOUNT_ID:secret:oppshield/dev/jwt-signing-secret"
        },
        {
          "name": "JWT_REFRESH_SECRET",
          "valueFrom": "arn:aws:secretsmanager:REGION:ACCOUNT_ID:secret:oppshield/dev/jwt-refresh-secret"
        },
        {
          "name": "PAYSTACK_SECRET_KEY",
          "valueFrom": "arn:aws:secretsmanager:REGION:ACCOUNT_ID:secret:oppshield/dev/paystack-secret-key"
        }
      ],
      "logConfiguration": {
        "logDriver": "awslogs",
        "options": {
          "awslogs-group": "/ecs/opsshield/dev",
          "awslogs-region": "REGION",
          "awslogs-stream-prefix": "ecs"
        }
      }
    }
  ]
}
